pacifica_downloader-0.4.1-py3.8-nspkg.pth
pacifica/downloader/__init__.py
pacifica/downloader/cartapi.py
pacifica/downloader/cloudevent.py
pacifica/downloader/downloader.py
pacifica/downloader/policy.py
pacifica/downloader/common/__init__.py
pacifica_downloader-0.4.1.dist-info/LICENSE
pacifica_downloader-0.4.1.dist-info/METADATA
pacifica_downloader-0.4.1.dist-info/WHEEL
pacifica_downloader-0.4.1.dist-info/namespace_packages.txt
pacifica_downloader-0.4.1.dist-info/top_level.txt
pacifica_downloader-0.4.1.dist-info/RECORD
