Metadata-Version: 2.1
Name: pacifica-downloader
Version: 0.4.1
Summary: Pacifica Python Downloader
Home-page: https://github.com/pacifica/pacifica-python-downloader/
Author: David Brown
Author-email: david.brown@pnnl.gov
License: UNKNOWN
Platform: UNKNOWN
Requires-Dist: requests
